{
  "status": "success",
  "message": "Water bottles data retrieved successfully",
  "totalItems": 50,
  "page": 1,
  "limit": 50,
  "timestamp": "2025-09-21T10:30:00Z",
  "data": [
    {
      "id": 1,
      "brand": "Mum",
      "color": "green",
      "capacity": "750ml",
      "price": 25,
      "currency": "BDT",
      "isAvailable": false,
      "stock": 0,
      "category": "mineral_water",
      "image": "https://via.placeholder.com/150?text=Bottle1",
      "createdAt": "2024-01-15T08:20:00Z",
      "updatedAt": "2025-09-20T14:45:00Z"
    },
    {
      "id": 2,
      "brand": "Fresh",
      "color": "transparent",
      "capacity": "1L",
      "price": 30,
      "currency": "BDT",
      "isAvailable": true,
      "stock": 15,
      "category": "mineral_water",
      "image": "https://via.placeholder.com/150?text=Bottle2",
      "createdAt": "2024-02-10T09:15:00Z",
      "updatedAt": "2025-09-19T16:30:00Z"
    },
    {
      "id": 3,
      "brand": "Kinley",
      "color": "white",
      "capacity": "1.5L",
      "price": 35,
      "currency": "BDT",
      "isAvailable": false,
      "stock": 0,
      "category": "mineral_water",
      "image": "https://via.placeholder.com/150?text=Bottle3",
      "createdAt": "2024-01-20T10:30:00Z",
      "updatedAt": "2025-09-18T12:15:00Z"
    },
    {
      "id": 4,
      "brand": "Spa",
      "color": "black",
      "capacity": "2L",
      "price": 40,
      "currency": "BDT",
      "isAvailable": true,
      "stock": 8,
      "category": "mineral_water",
      "image": "https://via.placeholder.com/150?text=Bottle4",
      "createdAt": "2024-03-05T14:45:00Z",
      "updatedAt": "2025-09-21T09:20:00Z"
    },
    {
      "id": 5,
      "brand": "Evian",
      "color": "red",
      "capacity": "500ml",
      "price": 45,
      "currency": "BDT",
      "isAvailable": false,
      "stock": 0,
      "category": "premium_water",
      "image": "https://via.placeholder.com/150?text=Bottle5",
      "createdAt": "2024-01-12T11:25:00Z",
      "updatedAt": "2025-09-17T15:40:00Z"
    },
    {
      "id": 6,
      "brand": "Bisleri",
      "color": "yellow",
      "capacity": "750ml",
      "price": 50,
      "currency": "BDT",
      "isAvailable": true,
      "stock": 22,
      "category": "mineral_water",
      "image": "https://via.placeholder.com/150?text=Bottle6",
      "createdAt": "2024-02-28T13:10:00Z",
      "updatedAt": "2025-09-20T17:55:00Z"
    },
    {
      "id": 7,
      "brand": "Nestle Pure",
      "color": "orange",
      "capacity": "1L",
      "price": 55,
      "currency": "BDT",
      "isAvailable": false,
      "stock": 0,
      "category": "premium_water",
      "image": "https://via.placeholder.com/150?text=Bottle7",
      "createdAt": "2024-03-15T16:20:00Z",
      "updatedAt": "2025-09-19T08:30:00Z"
    },
    {
      "id": 8,
      "brand": "Dasani",
      "color": "purple",
      "capacity": "1.5L",
      "price": 60,
      "currency": "BDT",
      "isAvailable": true,
      "stock": 12,
      "category": "premium_water",
      "image": "https://via.placeholder.com/150?text=Bottle8",
      "createdAt": "2024-01-25T07:45:00Z",
      "updatedAt": "2025-09-21T10:15:00Z"
    },
    {
      "id": 9,
      "brand": "Pran",
      "color": "pink",
      "capacity": "2L",
      "price": 65,
      "currency": "BDT",
      "isAvailable": false,
      "stock": 0,
      "category": "local_water",
      "image": "https://via.placeholder.com/150?text=Bottle9",
      "createdAt": "2024-02-14T12:35:00Z",
      "updatedAt": "2025-09-16T14:20:00Z"
    },
    {
      "id": 10,
      "brand": "Aquafina",
      "color": "blue",
      "capacity": "500ml",
      "price": 70,
      "currency": "BDT",
      "isAvailable": true,
      "stock": 18,
      "category": "premium_water",
      "image": "https://via.placeholder.com/150?text=Bottle10",
      "createdAt": "2024-03-22T09:50:00Z",
      "updatedAt": "2025-09-20T11:40:00Z"
    },
    {
      "id": 11,
      "brand": "Mum",
      "color": "green",
      "capacity": "750ml",
      "price": 25,
      "currency": "BDT",
      "isAvailable": true,
      "stock": 25,
      "category": "mineral_water",
      "image": "https://via.placeholder.com/150?text=Bottle11",
      "createdAt": "2024-01-15T08:20:00Z",
      "updatedAt": "2025-09-21T08:10:00Z"
    },
    {
      "id": 12,
      "brand": "Fresh",
      "color": "transparent",
      "capacity": "1L",
      "price": 30,
      "currency": "BDT",
      "isAvailable": true,
      "stock": 30,
      "category": "mineral_water",
      "image": "https://via.placeholder.com/150?text=Bottle12",
      "createdAt": "2024-02-10T09:15:00Z",
      "updatedAt": "2025-09-20T16:25:00Z"
    },
    {
      "id": 13,
      "brand": "Kinley",
      "color": "white",
      "capacity": "1.5L",
      "price": 35,
      "currency": "BDT",
      "isAvailable": false,
      "stock": 0,
      "category": "mineral_water",
      "image": "https://via.placeholder.com/150?text=Bottle13",
      "createdAt": "2024-01-20T10:30:00Z",
      "updatedAt": "2025-09-18T13:45:00Z"
    },
    {
      "id": 14,
      "brand": "Spa",
      "color": "black",
      "capacity": "2L",
      "price": 40,
      "currency": "BDT",
      "isAvailable": true,
      "stock": 14,
      "category": "mineral_water",
      "image": "https://via.placeholder.com/150?text=Bottle14",
      "createdAt": "2024-03-05T14:45:00Z",
      "updatedAt": "2025-09-19T10:30:00Z"
    },
    {
      "id": 15,
      "brand": "Evian",
      "color": "red",
      "capacity": "500ml",
      "price": 45,
      "currency": "BDT",
      "isAvailable": false,
      "stock": 0,
      "category": "premium_water",
      "image": "https://via.placeholder.com/150?text=Bottle15",
      "createdAt": "2024-01-12T11:25:00Z",
      "updatedAt": "2025-09-17T09:15:00Z"
    },
    {
      "id": 16,
      "brand": "Bisleri",
      "color": "yellow",
      "capacity": "750ml",
      "price": 50,
      "currency": "BDT",
      "isAvailable": true,
      "stock": 19,
      "category": "mineral_water",
      "image": "https://via.placeholder.com/150?text=Bottle16",
      "createdAt": "2024-02-28T13:10:00Z",
      "updatedAt": "2025-09-21T07:50:00Z"
    },
    {
      "id": 17,
      "brand": "Nestle Pure",
      "color": "orange",
      "capacity": "1L",
      "price": 55,
      "currency": "BDT",
      "isAvailable": false,
      "stock": 0,
      "category": "premium_water",
      "image": "https://via.placeholder.com/150?text=Bottle17",
      "createdAt": "2024-03-15T16:20:00Z",
      "updatedAt": "2025-09-20T12:35:00Z"
    },
    {
      "id": 18,
      "brand": "Dasani",
      "color": "purple",
      "capacity": "1.5L",
      "price": 60,
      "currency": "BDT",
      "isAvailable": true,
      "stock": 7,
      "category": "premium_water",
      "image": "https://via.placeholder.com/150?text=Bottle18",
      "createdAt": "2024-01-25T07:45:00Z",
      "updatedAt": "2025-09-19T15:20:00Z"
    },
    {
      "id": 19,
      "brand": "Pran",
      "color": "pink",
      "capacity": "2L",
      "price": 65,
      "currency": "BDT",
      "isAvailable": false,
      "stock": 0,
      "category": "local_water",
      "image": "https://via.placeholder.com/150?text=Bottle19",
      "createdAt": "2024-02-14T12:35:00Z",
      "updatedAt": "2025-09-18T11:10:00Z"
    },
    {
      "id": 20,
      "brand": "Aquafina",
      "color": "blue",
      "capacity": "500ml",
      "price": 70,
      "currency": "BDT",
      "isAvailable": true,
      "stock": 21,
      "category": "premium_water",
      "image": "https://via.placeholder.com/150?text=Bottle20",
      "createdAt": "2024-03-22T09:50:00Z",
      "updatedAt": "2025-09-21T09:45:00Z"
    },
    {
      "id": 21,
      "brand": "Smart Water",
      "color": "transparent",
      "capacity": "330ml",
      "price": 22,
      "currency": "BDT",
      "isAvailable": true,
      "stock": 35,
      "category": "premium_water",
      "image": "https://via.placeholder.com/150?text=Bottle21",
      "createdAt": "2024-04-01T10:15:00Z",
      "updatedAt": "2025-09-20T14:30:00Z"
    },
    {
      "id": 22,
      "brand": "Fiji",
      "color": "blue",
      "capacity": "500ml",
      "price": 75,
      "currency": "BDT",
      "isAvailable": false,
      "stock": 0,
      "category": "premium_water",
      "image": "https://via.placeholder.com/150?text=Bottle22",
      "createdAt": "2024-03-18T11:40:00Z",
      "updatedAt": "2025-09-17T16:25:00Z"
    },
    {
      "id": 23,
      "brand": "Volvic",
      "color": "light blue",
      "capacity": "750ml",
      "price": 42,
      "currency": "BDT",
      "isAvailable": true,
      "stock": 16,
      "category": "mineral_water",
      "image": "https://via.placeholder.com/150?text=Bottle23",
      "createdAt": "2024-04-05T13:25:00Z",
      "updatedAt": "2025-09-19T12:40:00Z"
    },
    {
      "id": 24,
      "brand": "Perrier",
      "color": "green",
      "capacity": "330ml",
      "price": 38,
      "currency": "BDT",
      "isAvailable": true,
      "stock": 28,
      "category": "sparkling_water",
      "image": "https://via.placeholder.com/150?text=Bottle24",
      "createdAt": "2024-02-22T08:30:00Z",
      "updatedAt": "2025-09-21T08:55:00Z"
    },
    {
      "id": 25,
      "brand": "San Pellegrino",
      "color": "dark green",
      "capacity": "500ml",
      "price": 48,
      "currency": "BDT",
      "isAvailable": false,
      "stock": 0,
      "category": "sparkling_water",
      "image": "https://via.placeholder.com/150?text=Bottle25",
      "createdAt": "2024-03-10T15:20:00Z",
      "updatedAt": "2025-09-18T10:15:00Z"
    },
    {
      "id": 26,
      "brand": "Ice Mountain",
      "color": "white",
      "capacity": "1L",
      "price": 32,
      "currency": "BDT",
      "isAvailable": true,
      "stock": 20,
      "category": "mineral_water",
      "image": "https://via.placeholder.com/150?text=Bottle26",
      "createdAt": "2024-01-30T09:45:00Z",
      "updatedAt": "2025-09-20T13:20:00Z"
    },
    {
      "id": 27,
      "brand": "Poland Spring",
      "color": "transparent",
      "capacity": "1.5L",
      "price": 36,
      "currency": "BDT",
      "isAvailable": false,
      "stock": 0,
      "category": "mineral_water",
      "image": "https://via.placeholder.com/150?text=Bottle27",
      "createdAt": "2024-04-12T12:10:00Z",
      "updatedAt": "2025-09-19T09:35:00Z"
    },
    {
      "id": 28,
      "brand": "Crystal Geyser",
      "color": "clear",
      "capacity": "2L",
      "price": 44,
      "currency": "BDT",
      "isAvailable": true,
      "stock": 11,
      "category": "mineral_water",
      "image": "https://via.placeholder.com/150?text=Bottle28",
      "createdAt": "2024-02-05T14:35:00Z",
      "updatedAt": "2025-09-21T10:05:00Z"
    },
    {
      "id": 29,
      "brand": "Arrowhead",
      "color": "blue",
      "capacity": "750ml",
      "price": 28,
      "currency": "BDT",
      "isAvailable": true,
      "stock": 24,
      "category": "mineral_water",
      "image": "https://via.placeholder.com/150?text=Bottle29",
      "createdAt": "2024-03-28T11:15:00Z",
      "updatedAt": "2025-09-20T15:45:00Z"
    },
    {
      "id": 30,
      "brand": "Deer Park",
      "color": "green",
      "capacity": "500ml",
      "price": 26,
      "currency": "BDT",
      "isAvailable": false,
      "stock": 0,
      "category": "mineral_water",
      "image": "https://via.placeholder.com/150?text=Bottle30",
      "createdAt": "2024-01-08T16:50:00Z",
      "updatedAt": "2025-09-17T14:30:00Z"
    },
    {
      "id": 31,
      "brand": "Ozarka",
      "color": "light blue",
      "capacity": "1L",
      "price": 34,
      "currency": "BDT",
      "isAvailable": true,
      "stock": 17,
      "category": "mineral_water",
      "image": "https://via.placeholder.com/150?text=Bottle31",
      "createdAt": "2024-04-20T10:25:00Z",
      "updatedAt": "2025-09-19T11:50:00Z"
    },
    {
      "id": 32,
      "brand": "Zephyrhills",
      "color": "white",
      "capacity": "330ml",
      "price": 24,
      "currency": "BDT",
      "isAvailable": false,
      "stock": 0,
      "category": "mineral_water",
      "image": "https://via.placeholder.com/150?text=Bottle32",
      "createdAt": "2024-02-18T13:40:00Z",
      "updatedAt": "2025-09-18T08:20:00Z"
    },
    {
      "id": 33,
      "brand": "Gerolsteiner",
      "color": "clear",
      "capacity": "750ml",
      "price": 52,
      "currency": "BDT",
      "isAvailable": true,
      "stock": 9,
      "category": "sparkling_water",
      "image": "https://via.placeholder.com/150?text=Bottle33",
      "createdAt": "2024-03-25T15:30:00Z",
      "updatedAt": "2025-09-21T09:10:00Z"
    },
    {
      "id": 34,
      "brand": "Badoit",
      "color": "dark green",
      "capacity": "330ml",
      "price": 45,
      "currency": "BDT",
      "isAvailable": true,
      "stock": 13,
      "category": "sparkling_water",
      "image": "https://via.placeholder.com/150?text=Bottle34",
      "createdAt": "2024-01-22T12:55:00Z",
      "updatedAt": "2025-09-20T10:15:00Z"
    },
    {
      "id": 35,
      "brand": "Highland Spring",
      "color": "transparent",
      "capacity": "1.5L",
      "price": 39,
      "currency": "BDT",
      "isAvailable": false,
      "stock": 0,
      "category": "mineral_water",
      "image": "https://via.placeholder.com/150?text=Bottle35",
      "createdAt": "2024-04-08T09:20:00Z",
      "updatedAt": "2025-09-17T15:25:00Z"
    },
    {
      "id": 36,
      "brand": "Buxton",
      "color": "blue",
      "capacity": "500ml",
      "price": 33,
      "currency": "BDT",
      "isAvailable": true,
      "stock": 26,
      "category": "mineral_water",
      "image": "https://via.placeholder.com/150?text=Bottle36",
      "createdAt": "2024-02-12T11:35:00Z",
      "updatedAt": "2025-09-19T13:45:00Z"
    },
    {
      "id": 37,
      "brand": "Harrogate",
      "color": "silver",
      "capacity": "750ml",
      "price": 47,
      "currency": "BDT",
      "isAvailable": false,
      "stock": 0,
      "category": "premium_water",
      "image": "https://via.placeholder.com/150?text=Bottle37",
      "createdAt": "2024-03-02T14:10:00Z",
      "updatedAt": "2025-09-18T16:40:00Z"
    },
    {
      "id": 38,
      "brand": "Malvern",
      "color": "green",
      "capacity": "2L",
      "price": 41,
      "currency": "BDT",
      "isAvailable": true,
      "stock": 10,
      "category": "mineral_water",
      "image": "https://via.placeholder.com/150?text=Bottle38",
      "createdAt": "2024-01-18T10:45:00Z",
      "updatedAt": "2025-09-20T12:30:00Z"
    },
    {
      "id": 39,
      "brand": "Ty Nant",
      "color": "cobalt blue",
      "capacity": "330ml",
      "price": 58,
      "currency": "BDT",
      "isAvailable": true,
      "stock": 6,
      "category": "premium_water",
      "image": "https://via.placeholder.com/150?text=Bottle39",
      "createdAt": "2024-04-15T16:25:00Z",
      "updatedAt": "2025-09-21T08:40:00Z"
    },
    {
      "id": 40,
      "brand": "Acqua Panna",
      "color": "clear",
      "capacity": "1L",
      "price": 56,
      "currency": "BDT",
      "isAvailable": false,
      "stock": 0,
      "category": "premium_water",
      "image": "https://via.placeholder.com/150?text=Bottle40",
      "createdAt": "2024-02-25T13:15:00Z",
      "updatedAt": "2025-09-19T14:55:00Z"
    },
    {
      "id": 41,
      "brand": "Vittel",
      "color": "pink",
      "capacity": "500ml",
      "price": 29,
      "currency": "BDT",
      "isAvailable": true,
      "stock": 32,
      "category": "mineral_water",
      "image": "https://via.placeholder.com/150?text=Bottle41",
      "createdAt": "2024-03-12T08:50:00Z",
      "updatedAt": "2025-09-20T09:25:00Z"
    },
    {
      "id": 42,
      "brand": "Contrex",
      "color": "purple",
      "capacity": "1.5L",
      "price": 37,
      "currency": "BDT",
      "isAvailable": false,
      "stock": 0,
      "category": "mineral_water",
      "image": "https://via.placeholder.com/150?text=Bottle42",
      "createdAt": "2024-01-28T15:40:00Z",
      "updatedAt": "2025-09-18T12:10:00Z"
    },
    {
      "id": 43,
      "brand": "Hépar",
      "color": "green",
      "capacity": "750ml",
      "price": 43,
      "currency": "BDT",
      "isAvailable": true,
      "stock": 14,
      "category": "mineral_water",
      "image": "https://via.placeholder.com/150?text=Bottle43",
      "createdAt": "2024-04-03T12:20:00Z",
      "updatedAt": "2025-09-19T10:45:00Z"
    },
    {
      "id": 44,
      "brand": "Badoit Rouge",
      "color": "red",
      "capacity": "330ml",
      "price": 49,
      "currency": "BDT",
      "isAvailable": true,
      "stock": 11,
      "category": "sparkling_water",
      "image": "https://via.placeholder.com/150?text=Bottle44",
      "createdAt": "2024-02-08T09:30:00Z",
      "updatedAt": "2025-09-21T07:35:00Z"
    },
    {
      "id": 45,
      "brand": "San Benedetto",
      "color": "light blue",
      "capacity": "2L",
      "price": 46,
      "currency": "BDT",
      "isAvailable": false,
      "stock": 0,
      "category": "mineral_water",
      "image": "https://via.placeholder.com/150?text=Bottle45",
      "createdAt": "2024-03-20T14:55:00Z",
      "updatedAt": "2025-09-17T11:20:00Z"
    },
    {
      "id": 46,
      "brand": "Ferrarelle",
      "color": "transparent",
      "capacity": "750ml",
      "price": 51,
      "currency": "BDT",
      "isAvailable": true,
      "stock": 8,
      "category": "sparkling_water",
      "image": "https://via.placeholder.com/150?text=Bottle46",
      "createdAt": "2024-01-05T11:10:00Z",
      "updatedAt": "2025-09-20T16:50:00Z"
    },
    {
      "id": 47,
      "brand": "Uliveto",
      "color": "blue",
      "capacity": "1L",
      "price": 35,
      "currency": "BDT",
      "isAvailable": false,
      "stock": 0,
      "category": "mineral_water",
      "image": "https://via.placeholder.com/150?text=Bottle47",
      "createdAt": "2024-04-10T13:45:00Z",
      "updatedAt": "2025-09-18T09:40:00Z"
    },
    {
      "id": 48,
      "brand": "Levissima",
      "color": "white",
      "capacity": "500ml",
      "price": 31,
      "currency": "BDT",
      "isAvailable": true,
      "stock": 27,
      "category": "mineral_water",
      "image": "https://via.placeholder.com/150?text=Bottle48",
      "createdAt": "2024-02-16T10:25:00Z",
      "updatedAt": "2025-09-19T15:30:00Z"
    },
    {
      "id": 49,
      "brand": "San Faustino",
      "color": "gold",
      "capacity": "330ml",
      "price": 53,
      "currency": "BDT",
      "isAvailable": true,
      "stock": 5,
      "category": "premium_water",
      "image": "https://via.placeholder.com/150?text=Bottle49",
      "createdAt": "2024-03-30T12:40:00Z",
      "updatedAt": "2025-09-20T11:15:00Z"
    },
    {
      "id": 50,
      "brand": "Rocchetta",
      "color": "emerald",
      "capacity": "1.5L",
      "price": 40,
      "currency": "BDT",
      "isAvailable": false,
      "stock": 0,
      "category": "mineral_water",
      "image": "https://via.placeholder.com/150?text=Bottle50",
      "createdAt": "2024-01-10T09:55:00Z",
      "updatedAt": "2025-09-17T13:25:00Z"
    }
  ],
  "pagination": {
    "currentPage": 1,
    "totalPages": 1,
    "hasNextPage": false,
    "hasPreviousPage": false
  },
  "filters": {
    "availableOnly": false,
    "minPrice": null,
    "maxPrice": null,
    "category": null,
    "brand": null
  },
  "summary": {
    "totalProducts": 50,
    "availableProducts": 26,
    "outOfStockProducts": 24,
    "categories": {
      "mineral_water": 28,
      "premium_water": 16,
      "sparkling_water": 5,
      "local_water": 1
    },
    "priceRange": {
      "min": 22,
      "max": 75,
      "average": 42.5
    }
  }
}
